algorithms/tests/test_backtracker.py
backtracker/__init__.py
backtracker/backtracker.py
backtracker/tests/__init__.py
backtracker/tests/test_backtracker.py
src/tests/test_backtracker.py
backtracker-0.0.5.dist-info/LICENSE
backtracker-0.0.5.dist-info/METADATA
backtracker-0.0.5.dist-info/WHEEL
backtracker-0.0.5.dist-info/top_level.txt
backtracker-0.0.5.dist-info/RECORD
